oneNeuron/__init__.py
oneNeuron/perceptron.py
PyPi_Yashwanth1119-0.0.3.dist-info/LICENSE
PyPi_Yashwanth1119-0.0.3.dist-info/METADATA
PyPi_Yashwanth1119-0.0.3.dist-info/WHEEL
PyPi_Yashwanth1119-0.0.3.dist-info/top_level.txt
PyPi_Yashwanth1119-0.0.3.dist-info/RECORD
