Metadata-Version: 2.1
Name: PyPi-Yashwanth1119
Version: 0.0.3
Summary: its an implimentation of Perceptron
Home-page: https://github.com/Yashwanth1119/PyPi
Author: Yashwanth1119
Author-email: yashwanthtvv@gmail.com
Project-URL: Bug Tracker, https://github.com/Yashwanth1119/PyPi/issues
Classifier: Programming Language :: Python :: 3
Classifier: License :: OSI Approved :: MIT License
Classifier: Operating System :: OS Independent
Requires-Python: >=3.7
License-File: LICENSE
Requires-Dist: numpy
Requires-Dist: tqdm
